tini/__init__.py
tini/app.py
tini_editor-1.2.2.dist-info/licenses/LICENSE
tini_editor-1.2.2.dist-info/METADATA
tini_editor-1.2.2.dist-info/WHEEL
tini_editor-1.2.2.dist-info/entry_points.txt
tini_editor-1.2.2.dist-info/top_level.txt
tini_editor-1.2.2.dist-info/RECORD
