Metadata-Version: 2.4
Name: tini-editor
Version: 1.2.2
Summary: A tiny terminal text editor built with Textual
Home-page: https://codeberg.org/WolfQuery/tini-editor
Author: WolfQuery
License: CC-BY-NC-SA-4.0
Keywords: textual,terminal,text editor,nano,tini
Classifier: Programming Language :: Python :: 3
Classifier: Development Status :: 5 - Production/Stable
Classifier: Environment :: Console :: Curses
Requires-Python: >=3.12
License-File: LICENSE
Requires-Dist: setuptools
Requires-Dist: windows-curses; platform_system == "Windows"
Requires-Dist: curses; platform_system != "Windows"
Dynamic: author
Dynamic: classifier
Dynamic: description
Dynamic: description-content-type
Dynamic: home-page
Dynamic: keywords
Dynamic: license
Dynamic: license-file
Dynamic: requires-dist
Dynamic: requires-python
Dynamic: summary
